espeakui/__init__.py
espeakui/espeak_urwid.py
espeakui/espeaker.py
espeakui/espeakui.py
espeakui/translate.py
espeakui_ng-0.2.2.dist-info/METADATA
espeakui_ng-0.2.2.dist-info/WHEEL
espeakui_ng-0.2.2.dist-info/top_level.txt
espeakui_ng-0.2.2.dist-info/RECORD
