Metadata-Version: 2.1
Name: espeakui-ng
Version: 0.2.2
Summary: A text-to-speech interface with mplayer-like bindings, using espeak-ng
Home-page: https://github.com/asrp/espeakui
Author: asrp
Author-email: asrp@email.com
License: UNKNOWN
Keywords: espeak ui tts
Platform: UNKNOWN
Requires-Dist: python-espeak-ng
Requires-Dist: guess-language-fast
Provides-Extra: full
Requires-Dist: urwid ; extra == 'full'
